navlie/__init__.py
navlie/datagen.py
navlie/filters.py
navlie/imm.py
navlie/types.py
navlie/utils.py
navlie/batch/__init__.py
navlie/batch/estimator.py
navlie/batch/losses.py
navlie/batch/problem.py
navlie/batch/residuals.py
navlie/lib/__init__.py
navlie/lib/camera.py
navlie/lib/datasets.py
navlie/lib/imu.py
navlie/lib/models.py
navlie/lib/preintegration.py
navlie/lib/states.py
navlie-0.0.1.dist-info/LICENSE
navlie-0.0.1.dist-info/METADATA
navlie-0.0.1.dist-info/WHEEL
navlie-0.0.1.dist-info/top_level.txt
navlie-0.0.1.dist-info/RECORD
